pyrvl-0.0.1.dist-info/WHEEL
pyrvl-0.0.1.dist-info/RECORD
pyrvl-0.0.1.dist-info/METADATA
pyrvl-0.0.1.dist-info/licenses/LICENSE
pyrvl/pyrvl.cpython-39-x86_64-linux-gnu.so
pyrvl/__init__.py
