Metadata-Version: 2.1
Name: pyrvl
Version: 0.0.1
Summary: Python Binding for RVL depth compression
Author-Email: "Andrew D. Wilson" <awilson@microsoft.com>
Maintainer-Email: Xudong Jiang <xudong.jiang@inf.ethz.ch>
Classifier: License :: OSI Approved :: MIT License
Project-URL: Homepage, https://github.com/xjiangan/pyrvl
Requires-Python: >=3.8
